lvx/__init__.py
lvx/clean_file.py
lvx/diff.py
lvx/lvx.py
livox_lvx-0.2.1.dist-info/LICENSE
livox_lvx-0.2.1.dist-info/METADATA
livox_lvx-0.2.1.dist-info/WHEEL
livox_lvx-0.2.1.dist-info/top_level.txt
livox_lvx-0.2.1.dist-info/RECORD
