Metadata-Version: 2.1
Name: livox-lvx
Version: 0.2.1
Summary: Library for reading, processing and writing .lvx files
Home-page: https://gitlab.com/twh2898/livox_lvx
Author: Thomas Harrison
Author-email: twh2898@vt.edu
License: UNKNOWN
Platform: UNKNOWN
Classifier: Development Status :: 3 - Alpha
Classifier: Intended Audience :: Developers
Classifier: Environment :: Console
Classifier: Operating System :: OS Independent
Classifier: License :: OSI Approved :: MIT License
Classifier: Programming Language :: Python :: 3.7
Classifier: Programming Language :: Python :: 3.8
Classifier: Programming Language :: Python :: 3.9
Classifier: Topic :: Utilities
Classifier: Typing :: Typed
Requires-Python: >=3.7
License-File: LICENSE
Requires-Dist: progress (>=1.5)
